<?xml version="1.0" ?>
<hair count="100" resolution="5" scale="13.17196289698283">
	<strand>
		<particle x="-2.0828444957733154" y="6.281143665313721" z="-0.25480759143829346"/>
		<particle x="-2.72029185295105" y="5.708568572998047" z="0.28336966037750244"/>
		<particle x="-3.0941905975341797" y="4.943039417266846" z="0.7610729932785034"/>
		<particle x="-3.4417552947998047" y="4.035127639770508" z="0.994329571723938"/>
		<particle x="-3.3148868083953857" y="3.167099714279175" z="1.5061166286468506"/>
	</strand>
	<strand>
		<particle x="-1.0877763032913208" y="6.802157878875732" z="-0.2144881635904312"/>
		<particle x="-1.8190977573394775" y="6.473210334777832" z="0.33359622955322266"/>
		<particle x="-2.423839807510376" y="5.8882856369018555" z="0.7381486892700195"/>
		<particle x="-2.8497607707977295" y="5.117077350616455" z="1.1017588376998901"/>
		<particle x="-3.0973780155181885" y="4.153053283691406" z="1.357485055923462"/>
	</strand>
	<strand>
		<particle x="-1.288345456123352" y="6.730647563934326" z="-0.04261372610926628"/>
		<particle x="-1.9268953800201416" y="6.348567485809326" z="0.5918737649917603"/>
		<particle x="-2.3918869495391846" y="5.734035015106201" z="1.1319172382354736"/>
		<particle x="-2.7024331092834473" y="4.945326328277588" z="1.5755006074905396"/>
		<particle x="-2.812903881072998" y="3.9861502647399902" z="1.9313580989837646"/>
	</strand>
	<strand>
		<particle x="-3.0598087310791016" y="5.16834020614624" z="-0.24020573496818542"/>
		<particle x="-3.5377886295318604" y="4.270569801330566" z="0.08565458655357361"/>
		<particle x="-3.8366506099700928" y="3.2817883491516113" z="0.296458899974823"/>
		<particle x="-3.6120049953460693" y="2.660963535308838" z="0.9418981671333313"/>
		<particle x="-3.6090235710144043" y="1.77469801902771" z="1.4935424327850342"/>
	</strand>
	<strand>
		<particle x="-0.11956213414669037" y="6.990251064300537" z="-0.21867385506629944"/>
		<particle x="-1.061644434928894" y="6.898068904876709" z="-0.27508965134620667"/>
		<particle x="-1.8762321472167969" y="6.5186848640441895" z="-0.393321692943573"/>
		<particle x="-2.571242332458496" y="5.907615661621094" z="-0.4387219250202179"/>
		<particle x="-3.138719081878662" y="5.092609405517578" z="-0.3195333182811737"/>
	</strand>
	<strand>
		<particle x="-0.10415985435247421" y="6.990251064300537" z="-0.19592857360839844"/>
		<particle x="-1.0480101108551025" y="6.903009414672852" z="-0.21927708387374878"/>
		<particle x="-1.868172287940979" y="6.530378341674805" z="-0.3115832805633545"/>
		<particle x="-2.5674264430999756" y="5.923741817474365" z="-0.34359222650527954"/>
		<particle x="-3.1272025108337402" y="5.103659629821777" z="-0.21972888708114624"/>
	</strand>
	<strand>
		<particle x="0.06209196895360947" y="6.990251064300537" z="-0.4142369329929352"/>
		<particle x="-0.754107654094696" y="6.9443488121032715" z="-0.8435989618301392"/>
		<particle x="-1.183222770690918" y="6.625035285949707" z="-1.6027817726135254"/>
		<particle x="-1.740112066268921" y="6.060006618499756" z="-2.1045572757720947"/>
		<particle x="-2.4126970767974854" y="5.351859092712402" z="-2.181262254714966"/>
	</strand>
	<strand>
		<particle x="0.03704317659139633" y="6.990238666534424" z="-0.4243153929710388"/>
		<particle x="-0.7714399099349976" y="6.937527179718018" z="-0.8756406307220459"/>
		<particle x="-1.2082021236419678" y="6.598562240600586" z="-1.6341006755828857"/>
		<particle x="-1.9205188751220703" y="6.084941864013672" z="-1.8409628868103027"/>
		<particle x="-2.4840152263641357" y="5.324958801269531" z="-2.124330520629883"/>
	</strand>
	<strand>
		<particle x="-3.305422306060791" y="4.478280067443848" z="0.44414156675338745"/>
		<particle x="-3.6134512424468994" y="3.4089879989624023" z="0.5414011478424072"/>
		<particle x="-3.6363751888275146" y="2.6322689056396484" z="0.9302240610122681"/>
		<particle x="-3.484649181365967" y="1.972386121749878" z="1.6647396087646484"/>
		<particle x="-3.491403102874756" y="0.9895810484886169" z="2.163283109664917"/>
	</strand>
	<strand>
		<particle x="-3.278663396835327" y="3.733513355255127" z="1.1734753847122192"/>
		<particle x="-3.2984964847564697" y="2.744088649749756" z="1.6543551683425903"/>
		<particle x="-3.3166615962982178" y="1.8152039051055908" z="2.1060895919799805"/>
		<particle x="-3.3291049003601074" y="0.886213481426239" z="2.5578320026397705"/>
		<particle x="-3.336949586868286" y="-0.10279446840286255" z="3.0398526191711426"/>
	</strand>
	<strand>
		<particle x="-3.1035449504852295" y="4.4782938957214355" z="1.0957319736480713"/>
		<particle x="-3.177733898162842" y="3.5100035667419434" z="1.594704031944275"/>
		<particle x="-3.188384771347046" y="2.5806775093078613" z="2.0332794189453125"/>
		<particle x="-3.2094218730926514" y="1.6542227268218994" z="2.4763550758361816"/>
		<particle x="-3.2269036769866943" y="0.6680376529693604" z="2.949470043182373"/>
	</strand>
	<strand>
		<particle x="-2.8091583251953125" y="5.168316841125488" z="0.9648127555847168"/>
		<particle x="-3.031139373779297" y="4.2845377922058105" z="1.5242140293121338"/>
		<particle x="-3.0470499992370605" y="3.3576221466064453" z="1.9487745761871338"/>
		<particle x="-3.066251277923584" y="2.4332733154296875" z="2.3718457221984863"/>
		<particle x="-3.0919430255889893" y="1.4528989791870117" z="2.8301196098327637"/>
	</strand>
	<strand>
		<particle x="-2.406818389892578" y="5.777064800262451" z="0.7857474088668823"/>
		<particle x="-2.764284133911133" y="5.019741535186768" z="1.4116063117980957"/>
		<particle x="-2.874866485595703" y="4.147356986999512" z="1.8799114227294922"/>
		<particle x="-2.896981716156006" y="3.220463275909424" z="2.26993465423584"/>
		<particle x="-2.940263032913208" y="2.247408866882324" z="2.7081170082092285"/>
	</strand>
	<strand>
		<particle x="-1.693316102027893" y="6.124929428100586" z="1.2437993288040161"/>
		<particle x="-1.9647252559661865" y="5.460933685302734" z="1.9734017848968506"/>
		<particle x="-2.0643277168273926" y="4.624795913696289" z="2.474553346633911"/>
		<particle x="-2.0865511894226074" y="3.7262752056121826" z="2.8846373558044434"/>
		<particle x="-2.1173136234283447" y="2.778491973876953" z="3.334137439727783"/>
	</strand>
	<strand>
		<particle x="-1.713937759399414" y="6.281147003173828" z="0.934050977230072"/>
		<particle x="-2.080240249633789" y="5.662031650543213" z="1.6566885709762573"/>
		<particle x="-2.2356276512145996" y="4.875344276428223" z="2.2091639041900635"/>
		<particle x="-2.275465250015259" y="3.976374626159668" z="2.6188769340515137"/>
		<particle x="-2.3133225440979004" y="3.020935535430908" z="3.0530505180358887"/>
	</strand>
	<strand>
		<particle x="-0.6485604047775269" y="6.902575969696045" z="0.17561569809913635"/>
		<particle x="-1.073485255241394" y="6.659755706787109" z="0.9848442077636719"/>
		<particle x="-1.772399663925171" y="6.158853054046631" z="1.3345460891723633"/>
		<particle x="-2.1859874725341797" y="5.441704273223877" z="1.8044354915618896"/>
		<particle x="-2.4401614665985107" y="4.543373107910156" z="2.218869686126709"/>
	</strand>
	<strand>
		<particle x="-2.7823829650878906" y="4.4782938957214355" z="1.6941262483596802"/>
		<particle x="-2.801046133041382" y="3.5000743865966797" z="2.1699914932250977"/>
		<particle x="-2.8229563236236572" y="2.5823025703430176" z="2.6178932189941406"/>
		<particle x="-2.842146635055542" y="1.6656415462493896" z="3.067974328994751"/>
		<particle x="-2.8542144298553467" y="0.6897048950195312" z="3.5482754707336426"/>
	</strand>
	<strand>
		<particle x="-2.354295015335083" y="4.478293418884277" z="2.2163469791412354"/>
		<particle x="-2.3811538219451904" y="3.5051636695861816" z="2.6884355545043945"/>
		<particle x="-2.404447078704834" y="2.592102289199829" z="3.132979393005371"/>
		<particle x="-2.420039176940918" y="1.679706335067749" z="3.5791146755218506"/>
		<particle x="-2.4279158115386963" y="0.708439826965332" z="4.055389404296875"/>
	</strand>
	<strand>
		<particle x="-2.130889654159546" y="5.168344974517822" z="1.9790740013122559"/>
		<particle x="-2.2240517139434814" y="4.259525775909424" z="2.5273427963256836"/>
		<particle x="-2.2298660278320312" y="3.3421576023101807" z="2.9467544555664062"/>
		<particle x="-2.2504220008850098" y="2.435910701751709" z="3.384726047515869"/>
		<particle x="-2.267620801925659" y="1.4716694355010986" z="3.853148937225342"/>
	</strand>
	<strand>
		<particle x="-1.3712934255599976" y="6.12490177154541" z="1.5553388595581055"/>
		<particle x="-1.5794389247894287" y="5.446765422821045" z="2.2914464473724365"/>
		<particle x="-1.6524722576141357" y="4.598773002624512" z="2.777134418487549"/>
		<particle x="-1.676395058631897" y="3.702899932861328" z="3.1859419345855713"/>
		<particle x="-1.7075917720794678" y="2.7593116760253906" z="3.6381821632385254"/>
	</strand>
	<strand>
		<particle x="-1.4500365257263184" y="6.281217575073242" z="1.255698323249817"/>
		<particle x="-1.7455947399139404" y="5.642536163330078" z="1.9936244487762451"/>
		<particle x="-1.869143009185791" y="4.836884021759033" z="2.527529001235962"/>
		<particle x="-1.8937567472457886" y="3.942598581314087" z="2.941648483276367"/>
		<particle x="-1.9237964153289795" y="2.9938642978668213" z="3.384192705154419"/>
	</strand>
	<strand>
		<particle x="-0.7941228747367859" y="6.661182403564453" z="0.9816826581954956"/>
		<particle x="-0.7349762916564941" y="6.2861223220825195" z="1.8509979248046875"/>
		<particle x="-1.2261872291564941" y="5.6373820304870605" z="2.3671631813049316"/>
		<particle x="-1.3571429252624512" y="4.808886528015137" z="2.852592706680298"/>
		<particle x="-1.3800907135009766" y="3.8569884300231934" z="3.2613167762756348"/>
	</strand>
	<strand>
		<particle x="-0.5835095643997192" y="6.124901294708252" z="1.9567031860351562"/>
		<particle x="-0.7381689548492432" y="5.41849946975708" z="2.6776914596557617"/>
		<particle x="-0.7815409302711487" y="4.5692949295043945" z="3.1599645614624023"/>
		<particle x="-0.8146591186523438" y="3.682455062866211" z="3.576446056365967"/>
		<particle x="-0.8512250185012817" y="2.7451140880584717" z="4.031652927398682"/>
	</strand>
	<strand>
		<particle x="-0.7673466205596924" y="6.281142711639404" z="1.7109960317611694"/>
		<particle x="-0.7437444925308228" y="5.66630220413208" z="2.4952566623687744"/>
		<particle x="-1.0146756172180176" y="4.850866794586182" z="2.94431734085083"/>
		<particle x="-1.024925708770752" y="3.954026460647583" z="3.3524794578552246"/>
		<particle x="-1.0499866008758545" y="3.0137505531311035" z="3.8030223846435547"/>
	</strand>
	<strand>
		<particle x="-0.2897256016731262" y="6.9025750160217285" z="0.4694097936153412"/>
		<particle x="-0.05510382354259491" y="6.676372051239014" z="1.376070499420166"/>
		<particle x="-0.42708343267440796" y="6.181603908538818" z="2.0913219451904297"/>
		<particle x="-0.8030783534049988" y="5.501775741577148" z="2.6304237842559814"/>
		<particle x="-0.9243136644363403" y="4.603236198425293" z="3.099419355392456"/>
	</strand>
	<strand>
		<particle x="-0.9281842708587646" y="3.4884135723114014" z="3.284149169921875"/>
		<particle x="-0.9560906887054443" y="2.5198261737823486" z="3.753561496734619"/>
		<particle x="-0.9686581492424011" y="1.6094019412994385" z="4.193137168884277"/>
		<particle x="-0.9822067618370056" y="0.6983370780944824" z="4.631469249725342"/>
		<particle x="-0.9909824132919312" y="-0.26888275146484375" z="5.104242324829102"/>
	</strand>
	<strand>
		<particle x="-1.317194938659668" y="3.733508348464966" z="3.1384825706481934"/>
		<particle x="-1.34164297580719" y="2.76495361328125" z="3.608191967010498"/>
		<particle x="-1.3566598892211914" y="1.8556510210037231" z="4.049765586853027"/>
		<particle x="-1.365693211555481" y="0.94632887840271" z="4.491472244262695"/>
		<particle x="-1.374383807182312" y="-0.021644294261932373" z="4.962859630584717"/>
	</strand>
	<strand>
		<particle x="-1.1281455755233765" y="5.168316841125488" z="2.6482505798339844"/>
		<particle x="-1.160233497619629" y="4.240679740905762" z="3.162308692932129"/>
		<particle x="-1.1767433881759644" y="3.3323910236358643" z="3.58087158203125"/>
		<particle x="-1.1935824155807495" y="2.433234691619873" z="4.016256809234619"/>
		<particle x="-1.2063175439834595" y="1.4765965938568115" z="4.481998443603516"/>
	</strand>
	<strand>
		<particle x="-0.6096085906028748" y="4.4782938957214355" z="3.1444082260131836"/>
		<particle x="-0.6375720500946045" y="3.5165088176727295" z="3.6123340129852295"/>
		<particle x="-0.6616040468215942" y="2.61542010307312" z="4.055411338806152"/>
		<particle x="-0.677855372428894" y="1.7169883251190186" z="4.503730297088623"/>
		<particle x="-0.704262375831604" y="0.7601048946380615" z="4.98071813583374"/>
	</strand>
	<strand>
		<particle x="-0.5249609351158142" y="4.689084529876709" z="3.065129280090332"/>
		<particle x="-0.5541619658470154" y="3.733431816101074" z="3.5279858112335205"/>
		<particle x="-0.5820363759994507" y="2.838280200958252" z="3.9665117263793945"/>
		<particle x="-0.5948464870452881" y="1.9469568729400635" z="4.412740230560303"/>
		<particle x="-0.6273104548454285" y="0.9990205764770508" z="4.889382362365723"/>
	</strand>
	<strand>
		<particle x="-0.20741598308086395" y="4.951111793518066" z="2.9643213748931885"/>
		<particle x="-0.23919545114040375" y="3.996779203414917" z="3.4294517040252686"/>
		<particle x="-0.27407658100128174" y="3.100947618484497" z="3.8661630153656006"/>
		<particle x="-0.30742353200912476" y="2.206005811691284" z="4.304633140563965"/>
		<particle x="-0.33456993103027344" y="1.2537693977355957" z="4.773937702178955"/>
	</strand>
	<strand>
		<particle x="-0.5515137910842896" y="5.1683173179626465" z="2.8190135955810547"/>
		<particle x="-0.5902696847915649" y="4.236454486846924" z="3.3223507404327393"/>
		<particle x="-0.6209788918495178" y="3.3323404788970947" z="3.7440836429595947"/>
		<particle x="-0.6449790596961975" y="2.4393277168273926" z="4.1867852210998535"/>
		<particle x="-0.649872362613678" y="1.489018440246582" z="4.6603851318359375"/>
	</strand>
	<strand>
		<particle x="-0.37479230761528015" y="6.281144142150879" z="1.8271114826202393"/>
		<particle x="-0.5187116861343384" y="5.624462127685547" z="2.5914392471313477"/>
		<particle x="-0.5992025136947632" y="4.793234348297119" z="3.090757369995117"/>
		<particle x="-0.6405912637710571" y="3.9000658988952637" z="3.4940195083618164"/>
		<particle x="-0.6812705397605896" y="2.960967779159546" z="3.94364595413208"/>
	</strand>
	<strand>
		<particle x="0.01313441526144743" y="6.902575492858887" z="0.5262013673782349"/>
		<particle x="0.5661309361457825" y="6.6914591789245605" z="1.2548680305480957"/>
		<particle x="0.4616134762763977" y="6.200316905975342" z="2.074930191040039"/>
		<particle x="0.5144320130348206" y="5.499151706695557" z="2.7101190090179443"/>
		<particle x="0.5937305092811584" y="4.59920597076416" z="3.1886813640594482"/>
	</strand>
	<strand>
		<particle x="0.046312734484672546" y="5.168316841125488" z="2.870375156402588"/>
		<particle x="0.028686942532658577" y="4.238085746765137" z="3.3774452209472656"/>
		<particle x="-0.020247409120202065" y="3.330631732940674" z="3.791033983230591"/>
		<particle x="-0.07769200950860977" y="2.4319345951080322" z="4.219851493835449"/>
		<particle x="-0.13680654764175415" y="1.4764912128448486" z="4.680053234100342"/>
	</strand>
	<strand>
		<particle x="0.5507093667984009" y="5.777065277099609" z="2.358103036880493"/>
		<particle x="0.5534540414810181" y="4.966533660888672" z="3.007174015045166"/>
		<particle x="0.5269080996513367" y="4.0620856285095215" z="3.417570114135742"/>
		<particle x="0.505785346031189" y="3.167107343673706" z="3.839738368988037"/>
		<particle x="0.4763161242008209" y="2.218019723892212" z="4.296750068664551"/>
	</strand>
	<strand>
		<particle x="0.43789875507354736" y="6.281192779541016" z="1.814149260520935"/>
		<particle x="0.45592665672302246" y="5.628005504608154" z="2.5962486267089844"/>
		<particle x="0.440923273563385" y="4.796980857849121" z="3.1038458347320557"/>
		<particle x="0.41190865635871887" y="3.9037909507751465" z="3.5102474689483643"/>
		<particle x="0.38211822509765625" y="2.9651432037353516" z="3.963552951812744"/>
	</strand>
	<strand>
		<particle x="1.1508889198303223" y="3.488415479660034" z="3.2144157886505127"/>
		<particle x="0.7684407234191895" y="2.559079170227051" z="3.5595133304595947"/>
		<particle x="0.6832172870635986" y="1.5833494663238525" z="3.8266103267669678"/>
		<particle x="0.7641969919204712" y="0.6813297271728516" z="4.2770185470581055"/>
		<particle x="0.8416109085083008" y="-0.279158353805542" z="4.755216121673584"/>
	</strand>
	<strand>
		<particle x="0.7490279674530029" y="3.733513355255127" z="3.3163914680480957"/>
		<particle x="0.7147729396820068" y="2.7647926807403564" z="3.785139560699463"/>
		<particle x="0.6798134446144104" y="1.8549599647521973" z="4.224669933319092"/>
		<particle x="0.6759227514266968" y="0.9464890956878662" z="4.668160438537598"/>
		<particle x="0.7414401769638062" y="-0.014175951480865479" z="5.147885322570801"/>
	</strand>
	<strand>
		<particle x="0.7093232274055481" y="4.4782938957214355" z="3.123936653137207"/>
		<particle x="0.6807674765586853" y="3.5138731002807617" z="3.591642379760742"/>
		<particle x="0.6549691557884216" y="2.60813045501709" z="4.030467510223389"/>
		<particle x="0.6393008232116699" y="1.702545166015625" z="4.47014856338501"/>
		<particle x="0.6688246130943298" y="0.741830587387085" z="4.944460868835449"/>
	</strand>
	<strand>
		<particle x="1.4158695936203003" y="3.733513593673706" z="3.0962977409362793"/>
		<particle x="1.0324406623840332" y="2.8008079528808594" z="3.4446663856506348"/>
		<particle x="0.9498018622398376" y="1.820587158203125" z="3.7164018154144287"/>
		<particle x="0.9481919407844543" y="0.9053835868835449" z="4.1615190505981445"/>
		<particle x="1.0150326490402222" y="-0.06031227111816406" z="4.641539096832275"/>
	</strand>
	<strand>
		<particle x="1.340553641319275" y="4.478292942047119" z="2.9155373573303223"/>
		<particle x="0.9943752884864807" y="3.5788228511810303" z="3.351797103881836"/>
		<particle x="0.9010939598083496" y="2.5835485458374023" z="3.573942184448242"/>
		<particle x="0.8736793994903564" y="1.6555366516113281" z="3.974498987197876"/>
		<particle x="0.9041910171508789" y="0.6918520927429199" z="4.452862739562988"/>
	</strand>
	<strand>
		<particle x="1.3780544996261597" y="5.586681842803955" z="2.1775128841400146"/>
		<particle x="1.2661231756210327" y="4.8203911781311035" z="2.8681421279907227"/>
		<particle x="1.1560258865356445" y="3.9042961597442627" z="3.2411575317382812"/>
		<particle x="1.0384538173675537" y="2.924483299255371" z="3.4191901683807373"/>
		<particle x="0.9877933263778687" y="1.9465248584747314" z="3.809828758239746"/>
	</strand>
	<strand>
		<particle x="1.0402452945709229" y="5.777064800262451" z="2.1963584423065186"/>
		<particle x="1.02340567111969" y="4.9858856201171875" z="2.870432138442993"/>
		<particle x="1.0222641229629517" y="4.082718849182129" z="3.2930097579956055"/>
		<particle x="0.9163060188293457" y="3.139293909072876" z="3.5875120162963867"/>
		<particle x="0.8653454184532166" y="2.1674365997314453" z="3.996150493621826"/>
	</strand>
	<strand>
		<particle x="1.9202675819396973" y="4.4782938957214355" z="2.5840253829956055"/>
		<particle x="1.661916732788086" y="3.5723228454589844" z="3.087817668914795"/>
		<particle x="1.5176246166229248" y="2.5779292583465576" z="3.3081440925598145"/>
		<particle x="1.4453256130218506" y="1.6308062076568604" z="3.6580419540405273"/>
		<particle x="1.4432183504104614" y="0.658015251159668" z="4.133563041687012"/>
	</strand>
	<strand>
		<particle x="1.7858256101608276" y="6.124879837036133" z="1.127481460571289"/>
		<particle x="1.9106169939041138" y="5.557518482208252" z="1.957773208618164"/>
		<particle x="2.076185703277588" y="4.727760314941406" z="2.463210344314575"/>
		<particle x="1.9969780445098877" y="3.8221123218536377" z="2.844405174255371"/>
		<particle x="1.8563964366912842" y="2.8084497451782227" z="3.100046157836914"/>
	</strand>
	<strand>
		<particle x="1.495522141456604" y="6.281142234802246" z="1.2087397575378418"/>
		<particle x="1.5568201541900635" y="5.759413242340088" z="2.062171459197998"/>
		<particle x="1.7384178638458252" y="4.957607746124268" z="2.589461326599121"/>
		<particle x="1.6769957542419434" y="4.056443691253662" z="2.982473850250244"/>
		<particle x="1.5659009218215942" y="3.034153938293457" z="3.22444486618042"/>
	</strand>
	<strand>
		<particle x="1.0514919757843018" y="6.661231517791748" z="0.763653039932251"/>
		<particle x="1.1499488353729248" y="6.31033182144165" z="1.6688477993011475"/>
		<particle x="1.4919157028198242" y="5.611499786376953" z="2.2364377975463867"/>
		<particle x="1.5612692832946777" y="4.8000946044921875" z="2.7670485973358154"/>
		<particle x="1.5317764282226562" y="3.820408344268799" z="3.1104350090026855"/>
	</strand>
	<strand>
		<particle x="2.998781442642212" y="3.733513832092285" z="1.7139767408370972"/>
		<particle x="2.899346351623535" y="2.7517428398132324" z="2.197221279144287"/>
		<particle x="2.7655115127563477" y="1.7937681674957275" z="2.580965042114258"/>
		<particle x="2.711045265197754" y="0.9980290532112122" z="3.200623035430908"/>
		<particle x="2.789889335632324" y="0.32284146547317505" z="4.038017749786377"/>
	</strand>
	<strand>
		<particle x="2.8388679027557373" y="4.478293418884277" z="1.6068710088729858"/>
		<particle x="2.807732582092285" y="3.523514747619629" z="2.1325275897979736"/>
		<particle x="2.6699411869049072" y="2.582498788833618" z="2.5225439071655273"/>
		<particle x="2.50288724899292" y="1.6200459003448486" z="2.844679355621338"/>
		<particle x="2.3648464679718018" y="0.5853266716003418" z="3.1843528747558594"/>
	</strand>
	<strand>
		<particle x="2.8315937519073486" y="4.951111316680908" z="1.1544028520584106"/>
		<particle x="2.989137887954712" y="4.055277347564697" z="1.7172744274139404"/>
		<particle x="2.8916878700256348" y="3.131110668182373" z="2.1353201866149902"/>
		<particle x="2.7577850818634033" y="2.195746421813965" z="2.5118041038513184"/>
		<particle x="2.6110727787017822" y="1.170642375946045" z="2.8360157012939453"/>
	</strand>
	<strand>
		<particle x="2.569857597351074" y="5.168316841125488" z="1.4269449710845947"/>
		<particle x="2.662135362625122" y="4.316919326782227" z="2.065298557281494"/>
		<particle x="2.5838451385498047" y="3.3833961486816406" z="2.45729923248291"/>
		<particle x="2.4107940196990967" y="2.432461977005005" z="2.7761712074279785"/>
		<particle x="2.269512891769409" y="1.3995366096496582" z="3.083324432373047"/>
	</strand>
	<strand>
		<particle x="2.20209002494812" y="5.777064800262451" z="1.1811156272888184"/>
		<particle x="2.402153730392456" y="5.059800148010254" z="1.9101290702819824"/>
		<particle x="2.4587602615356445" y="4.17657470703125" z="2.3704371452331543"/>
		<particle x="2.317721366882324" y="3.2417478561401367" z="2.7098288536071777"/>
		<particle x="2.1781296730041504" y="2.2218527793884277" z="3.0094714164733887"/>
	</strand>
	<strand>
		<particle x="1.2300623655319214" y="6.661206245422363" z="0.531697690486908"/>
		<particle x="1.4580771923065186" y="6.437219619750977" z="1.4338946342468262"/>
		<particle x="1.9234102964401245" y="5.711517333984375" z="1.8739588260650635"/>
		<particle x="2.0951952934265137" y="4.873337268829346" z="2.3443515300750732"/>
		<particle x="2.141209602355957" y="3.9058542251586914" z="2.7201709747314453"/>
	</strand>
	<strand>
		<particle x="1.3613629341125488" y="6.661141872406006" z="0.26823991537094116"/>
		<particle x="1.6254738569259644" y="6.500044822692871" z="1.182816743850708"/>
		<particle x="2.217592716217041" y="5.811756134033203" z="1.4955048561096191"/>
		<particle x="2.545175075531006" y="4.96256160736084" z="1.798830509185791"/>
		<particle x="2.6557276248931885" y="4.009289741516113" z="2.2000253200531006"/>
	</strand>
	<strand>
		<particle x="3.142454147338867" y="4.4782938957214355" z="0.9987795352935791"/>
		<particle x="3.2136809825897217" y="3.5122182369232178" z="1.5088996887207031"/>
		<particle x="3.136160135269165" y="2.567319393157959" z="1.9301602840423584"/>
		<particle x="3.0920145511627197" y="1.7691612243652344" z="2.553828001022339"/>
		<particle x="3.173740863800049" y="1.1674578189849854" z="3.435148000717163"/>
	</strand>
	<strand>
		<particle x="0.776206910610199" y="6.9025750160217285" z="-0.14246471226215363"/>
		<particle x="1.395203709602356" y="6.747929096221924" z="0.6196677088737488"/>
		<particle x="2.0317015647888184" y="6.398540496826172" z="0.8059147000312805"/>
		<particle x="2.665259838104248" y="5.782468795776367" z="0.4483411908149719"/>
		<particle x="3.2006402015686035" y="4.978305816650391" z="0.1611374020576477"/>
	</strand>
	<strand>
		<particle x="3.0597972869873047" y="5.168316841125488" z="-0.33581945300102234"/>
		<particle x="3.490053176879883" y="4.3375043869018555" z="0.1732712686061859"/>
		<particle x="3.628422737121582" y="3.4660162925720215" z="0.6891728639602661"/>
		<particle x="3.780088424682617" y="2.8821048736572266" z="1.4730788469314575"/>
		<particle x="3.9962053298950195" y="2.4927594661712646" z="2.4252312183380127"/>
	</strand>
	<strand>
		<particle x="2.9325902462005615" y="5.35701322555542" z="-0.39704930782318115"/>
		<particle x="3.406181573867798" y="4.5582075119018555" z="0.09100547432899475"/>
		<particle x="3.6119065284729004" y="3.6889641284942627" z="0.5545015335083008"/>
		<particle x="3.7592084407806396" y="3.0307695865631104" z="1.259131908416748"/>
		<particle x="3.983530044555664" y="2.653719186782837" z="2.1956520080566406"/>
	</strand>
	<strand>
		<particle x="2.7341034412384033" y="5.586681842803955" z="-0.6586689949035645"/>
		<particle x="3.327467441558838" y="4.809754371643066" z="-0.2876887023448944"/>
		<particle x="3.6670050621032715" y="3.9672648906707764" z="0.12237140536308289"/>
		<particle x="3.861936569213867" y="3.2798562049865723" z="0.7908515930175781"/>
		<particle x="4.114082336425781" y="2.8592734336853027" z="1.7027873992919922"/>
	</strand>
	<strand>
		<particle x="2.6216957569122314" y="5.777064800262451" z="-0.32931503653526306"/>
		<particle x="3.180616617202759" y="5.031494140625" z="0.14297714829444885"/>
		<particle x="3.4690372943878174" y="4.160826206207275" z="0.5235214233398438"/>
		<particle x="3.5887887477874756" y="3.2650656700134277" z="0.9767686128616333"/>
		<particle x="3.7978458404541016" y="2.7070136070251465" z="1.8197638988494873"/>
	</strand>
	<strand>
		<particle x="2.082836866378784" y="6.281106948852539" z="-0.3212202489376068"/>
		<particle x="2.63092303276062" y="5.805148601531982" z="0.3042295277118683"/>
		<particle x="3.2106003761291504" y="5.007070541381836" z="0.2752542793750763"/>
		<particle x="3.500762462615967" y="4.083756446838379" z="0.4931006133556366"/>
		<particle x="3.6248745918273926" y="3.0380749702453613" z="0.636742353439331"/>
	</strand>
	<strand>
		<particle x="1.4639512300491333" y="6.661187171936035" z="-0.31185656785964966"/>
		<particle x="1.8166592121124268" y="6.477442741394043" z="0.5102109909057617"/>
		<particle x="2.590566396713257" y="5.866528034210205" z="0.4384578764438629"/>
		<particle x="3.121438503265381" y="5.146463394165039" z="0.10581547021865845"/>
		<particle x="3.591425895690918" y="4.24768590927124" z="0.03923424333333969"/>
	</strand>
	<strand>
		<particle x="2.036548137664795" y="6.281144142150879" z="-0.7400218844413757"/>
		<particle x="2.6764848232269287" y="5.819025993347168" z="-0.21750253438949585"/>
		<particle x="3.2366161346435547" y="5.022554397583008" z="-0.39458101987838745"/>
		<particle x="3.6532227993011475" y="4.143121242523193" z="-0.20063646137714386"/>
		<particle x="3.973522186279297" y="3.3214242458343506" z="0.3389885425567627"/>
	</strand>
	<strand>
		<particle x="1.5712056159973145" y="6.545083522796631" z="-0.8378067016601562"/>
		<particle x="2.4078750610351562" y="6.025506019592285" z="-0.8602452278137207"/>
		<particle x="3.0111184120178223" y="5.2942962646484375" z="-0.8267746567726135"/>
		<particle x="3.499049425125122" y="4.454033851623535" z="-0.8210474252700806"/>
		<particle x="4.140737533569336" y="3.7438926696777344" z="-0.5340679883956909"/>
	</strand>
	<strand>
		<particle x="1.4313169717788696" y="6.6611833572387695" z="-0.6062034368515015"/>
		<particle x="1.8485653400421143" y="6.479964733123779" z="0.1757291555404663"/>
		<particle x="2.5723729133605957" y="5.932461261749268" z="-0.19697970151901245"/>
		<particle x="3.067992687225342" y="5.22451114654541" z="-0.5744869112968445"/>
		<particle x="3.570448398590088" y="4.330828666687012" z="-0.6571945548057556"/>
	</strand>
	<strand>
		<particle x="0.7710821032524109" y="6.9025750160217285" z="-0.46015962958335876"/>
		<particle x="1.0031228065490723" y="6.739171981811523" z="-1.3840913772583008"/>
		<particle x="1.5609352588653564" y="6.252462863922119" z="-1.9700583219528198"/>
		<particle x="2.0940027236938477" y="5.559915542602539" z="-2.327547550201416"/>
		<particle x="2.7955715656280518" y="4.8719940185546875" z="-2.241702079772949"/>
	</strand>
	<strand>
		<particle x="1.911987543106079" y="6.281142711639404" z="-1.1414501667022705"/>
		<particle x="2.697173595428467" y="5.659849166870117" z="-1.0626972913742065"/>
		<particle x="3.247087240219116" y="4.861948013305664" z="-0.9471956491470337"/>
		<particle x="3.798715591430664" y="4.1537184715271" z="-0.6090133190155029"/>
		<particle x="4.344549179077148" y="3.703371524810791" z="0.10511016845703125"/>
	</strand>
	<strand>
		<particle x="0.7237319350242615" y="6.90257453918457" z="-0.6121286153793335"/>
		<particle x="0.6313390135765076" y="6.76636266708374" z="-1.5596747398376465"/>
		<particle x="0.9025753736495972" y="6.3066840171813965" z="-2.335028648376465"/>
		<particle x="0.9407710433006287" y="5.6520209312438965" z="-3.023407220840454"/>
		<particle x="1.0097293853759766" y="4.7885026931762695" z="-3.5639431476593018"/>
	</strand>
	<strand>
		<particle x="2.518399238586426" y="5.1683173179626465" z="-2.0824718475341797"/>
		<particle x="3.2804088592529297" y="4.629340171813965" z="-1.6507412195205688"/>
		<particle x="3.970411777496338" y="4.274193286895752" z="-1.0800549983978271"/>
		<particle x="4.504751682281494" y="4.0349578857421875" z="-0.31493639945983887"/>
		<particle x="4.888330936431885" y="3.8986358642578125" z="0.6311679482460022"/>
	</strand>
	<strand>
		<particle x="1.8255075216293335" y="5.777064800262451" z="-2.230790853500366"/>
		<particle x="2.6010680198669434" y="5.133039474487305" z="-2.1388955116271973"/>
		<particle x="3.3320536613464355" y="4.68638801574707" z="-1.725912094116211"/>
		<particle x="4.035700798034668" y="4.364099502563477" z="-1.1830506324768066"/>
		<particle x="4.683367729187012" y="4.085384845733643" z="-0.4647436738014221"/>
	</strand>
	<strand>
		<particle x="1.3712961673736572" y="6.124901294708252" z="-2.1313705444335938"/>
		<particle x="2.0745091438293457" y="5.475476264953613" z="-2.421333074569702"/>
		<particle x="2.793252944946289" y="4.905022621154785" z="-2.1993370056152344"/>
		<particle x="3.533024787902832" y="4.540760040283203" z="-1.7563469409942627"/>
		<particle x="4.288985729217529" y="4.245166778564453" z="-1.189156174659729"/>
	</strand>
	<strand>
		<particle x="1.450047254562378" y="6.2811431884765625" z="-1.8317501544952393"/>
		<particle x="2.1848368644714355" y="5.652168273925781" z="-2.0990421772003174"/>
		<particle x="2.8626646995544434" y="5.0100250244140625" z="-1.9710605144500732"/>
		<particle x="3.5882315635681152" y="4.600158214569092" z="-1.536799669265747"/>
		<particle x="4.330925941467285" y="4.296268463134766" z="-0.9548307657241821"/>
	</strand>
	<strand>
		<particle x="1.018839955329895" y="6.661182403564453" z="-1.3733996152877808"/>
		<particle x="1.6215791702270508" y="6.1810431480407715" z="-1.998807668685913"/>
		<particle x="2.165698528289795" y="5.478003025054932" z="-2.332871913909912"/>
		<particle x="2.838212251663208" y="4.859918594360352" z="-2.1698267459869385"/>
		<particle x="3.608421802520752" y="4.433006286621094" z="-1.7276175022125244"/>
	</strand>
	<strand>
		<particle x="2.130905866622925" y="5.1683173179626465" z="-2.555096387863159"/>
		<particle x="2.9336090087890625" y="4.730152606964111" z="-2.109267234802246"/>
		<particle x="3.6680779457092285" y="4.3884663581848145" z="-1.6020947694778442"/>
		<particle x="4.322826385498047" y="4.1151885986328125" z="-0.9617937207221985"/>
		<particle x="4.826615333557129" y="3.9164345264434814" z="-0.09598660469055176"/>
	</strand>
	<strand>
		<particle x="0.26006439328193665" y="6.831083297729492" z="-1.2876402139663696"/>
		<particle x="0.3623107671737671" y="6.602789402008057" z="-2.235032081604004"/>
		<particle x="0.14155682921409607" y="6.128133773803711" z="-3.0244994163513184"/>
		<particle x="-0.10702474415302277" y="5.290816307067871" z="-3.485215902328491"/>
		<particle x="0.537763237953186" y="4.773083686828613" z="-3.8714098930358887"/>
	</strand>
	<strand>
		<particle x="0.28972816467285156" y="6.9026103019714355" z="-1.045434594154358"/>
		<particle x="0.24217459559440613" y="6.712209224700928" z="-2.0031821727752686"/>
		<particle x="0.4158836007118225" y="6.292349815368652" z="-2.834289073944092"/>
		<particle x="-0.009238988161087036" y="5.6003570556640625" z="-3.3133952617645264"/>
		<particle x="0.3277352452278137" y="4.864040851593018" z="-3.766026735305786"/>
	</strand>
	<strand>
		<particle x="0.8181251883506775" y="4.951111793518066" z="-3.436091423034668"/>
		<particle x="1.7331054210662842" y="4.561830997467041" z="-3.3729801177978516"/>
		<particle x="2.5472865104675293" y="4.275028705596924" z="-2.9896514415740967"/>
		<particle x="3.313295364379883" y="4.035975933074951" z="-2.494997501373291"/>
		<particle x="4.094315052032471" y="3.8163986206054688" z="-1.9034013748168945"/>
	</strand>
	<strand>
		<particle x="1.1281483173370361" y="5.168316841125488" z="-3.224282741546631"/>
		<particle x="1.9949647188186646" y="4.670848369598389" z="-3.142930507659912"/>
		<particle x="2.7915549278259277" y="4.358712196350098" z="-2.736781597137451"/>
		<particle x="3.54648494720459" y="4.111738204956055" z="-2.2275569438934326"/>
		<particle x="4.318006992340088" y="3.8893826007843018" z="-1.6237707138061523"/>
	</strand>
	<strand>
		<particle x="0.9663162231445312" y="5.777064800262451" z="-2.8040006160736084"/>
		<particle x="1.4542837142944336" y="5.024654865264893" z="-3.2539713382720947"/>
		<particle x="2.2823026180267334" y="4.597856521606445" z="-3.0600056648254395"/>
		<particle x="3.053548812866211" y="4.318467140197754" z="-2.602480173110962"/>
		<particle x="3.8346128463745117" y="4.073417663574219" z="-2.0374536514282227"/>
	</strand>
	<strand>
		<particle x="0.4722273051738739" y="5.777064800262451" z="-2.950249433517456"/>
		<particle x="0.8646889925003052" y="5.052507400512695" z="-3.523531913757324"/>
		<particle x="1.7205941677093506" y="4.659925937652588" z="-3.5190937519073486"/>
		<particle x="2.5266036987304688" y="4.378226280212402" z="-3.128791093826294"/>
		<particle x="3.3316142559051514" y="4.125025749206543" z="-2.6063523292541504"/>
	</strand>
	<strand>
		<particle x="0.1410074234008789" y="6.902583122253418" z="-1.0892314910888672"/>
		<particle x="-0.0345643013715744" y="6.7079691886901855" z="-2.0290684700012207"/>
		<particle x="-0.4594108462333679" y="6.218237400054932" z="-2.717209815979004"/>
		<particle x="-1.096816062927246" y="5.626352310180664" z="-2.995166301727295"/>
		<particle x="-1.4328134059906006" y="4.8206634521484375" z="-3.449495553970337"/>
	</strand>
	<strand>
		<particle x="0.5515162348747253" y="5.168316841125488" z="-3.3950462341308594"/>
		<particle x="1.423081874847412" y="4.725286483764648" z="-3.5736210346221924"/>
		<particle x="2.262908458709717" y="4.418724536895752" z="-3.2669036388397217"/>
		<particle x="3.038141965866089" y="4.172007083892822" z="-2.79197359085083"/>
		<particle x="3.8221495151519775" y="3.947812557220459" z="-2.209293842315674"/>
	</strand>
	<strand>
		<particle x="-0.04000753164291382" y="5.777065277099609" z="-2.994189977645874"/>
		<particle x="0.39782920479774475" y="5.095248222351074" z="-3.5982887744903564"/>
		<particle x="1.24275803565979" y="4.7424821853637695" z="-3.7965426445007324"/>
		<particle x="2.0902352333068848" y="4.453929901123047" z="-3.53731107711792"/>
		<particle x="2.9207613468170166" y="4.190154075622559" z="-3.0631251335144043"/>
	</strand>
	<strand>
		<particle x="-0.032174766063690186" y="6.281136989593506" z="-2.437983274459839"/>
		<particle x="0.1493782103061676" y="5.7626447677612305" z="-3.2486798763275146"/>
		<particle x="0.2672942578792572" y="5.03663969039917" z="-3.6692376136779785"/>
		<particle x="1.1420114040374756" y="4.726456165313721" z="-3.9401938915252686"/>
		<particle x="2.062715768814087" y="4.4269633293151855" z="-3.8462400436401367"/>
	</strand>
	<strand>
		<particle x="-0.3082537055015564" y="6.661182403564453" z="-1.765453577041626"/>
		<particle x="-0.49581003189086914" y="6.26152229309082" z="-2.6206231117248535"/>
		<particle x="-1.2849791049957275" y="5.789364337921143" z="-2.7681350708007812"/>
		<particle x="-2.062028169631958" y="5.312171459197998" z="-2.584862232208252"/>
		<particle x="-2.84818696975708" y="4.813100814819336" z="-2.2726101875305176"/>
	</strand>
	<strand>
		<particle x="-0.5507075786590576" y="5.777064323425293" z="-2.9341354370117188"/>
		<particle x="-0.17285874485969543" y="5.086052417755127" z="-3.562331438064575"/>
		<particle x="0.6571588516235352" y="4.7336015701293945" z="-3.876924991607666"/>
		<particle x="1.5294744968414307" y="4.437244892120361" z="-3.858703136444092"/>
		<particle x="2.4109885692596436" y="4.143916130065918" z="-3.5139071941375732"/>
	</strand>
	<strand>
		<particle x="-1.213719129562378" y="5.168316841125488" z="-3.1876955032348633"/>
		<particle x="-0.4311712980270386" y="4.794483184814453" z="-3.7028777599334717"/>
		<particle x="0.426652193069458" y="4.499421119689941" z="-3.980029582977295"/>
		<particle x="1.3186485767364502" y="4.226945877075195" z="-3.99450421333313"/>
		<particle x="2.2236766815185547" y="3.9391047954559326" z="-3.674665927886963"/>
	</strand>
	<strand>
		<particle x="-0.5815725922584534" y="6.661211013793945" z="-1.6749707460403442"/>
		<particle x="-0.8564590215682983" y="6.260159492492676" z="-2.4479691982269287"/>
		<particle x="-1.7449026107788086" y="5.912672519683838" z="-2.27896785736084"/>
		<particle x="-2.4532253742218018" y="5.357531547546387" z="-2.0755434036254883"/>
		<particle x="-3.188828468322754" y="4.749012470245361" z="-1.8072444200515747"/>
	</strand>
	<strand>
		<particle x="-0.3139883279800415" y="6.9025750160217285" z="-1.0350687503814697"/>
		<particle x="-1.0307164192199707" y="6.658234596252441" z="-1.6178605556488037"/>
		<particle x="-1.8566288948059082" y="6.265761852264404" z="-1.5620124340057373"/>
		<particle x="-2.5420212745666504" y="5.665624618530273" z="-1.5072410106658936"/>
		<particle x="-3.0867738723754883" y="4.816041946411133" z="-1.5681822299957275"/>
	</strand>
	<strand>
		<particle x="-0.44915175437927246" y="6.9025750160217285" z="-0.9574798345565796"/>
		<particle x="-1.308497667312622" y="6.6750030517578125" z="-1.2416698932647705"/>
		<particle x="-2.101986885070801" y="6.2736382484436035" z="-1.0343170166015625"/>
		<particle x="-2.746703624725342" y="5.59282112121582" z="-1.1009691953659058"/>
		<particle x="-3.276986837387085" y="4.733745574951172" z="-1.1661925315856934"/>
	</strand>
	<strand>
		<particle x="-1.489798665046692" y="5.777064323425293" z="-2.5151736736297607"/>
		<particle x="-2.3039748668670654" y="5.187713623046875" z="-2.4885482788085938"/>
		<particle x="-2.969064235687256" y="4.557319641113281" z="-2.1972692012786865"/>
		<particle x="-3.5478856563568115" y="3.843034267425537" z="-1.8803997039794922"/>
		<particle x="-4.086958885192871" y="3.2509682178497314" z="-1.2475509643554688"/>
	</strand>
	<strand>
		<particle x="-0.8325526714324951" y="6.661182403564453" z="-1.5312291383743286"/>
		<particle x="-1.59663987159729" y="6.251414775848389" z="-1.9032241106033325"/>
		<particle x="-2.3694796562194824" y="5.79457950592041" z="-1.6392934322357178"/>
		<particle x="-2.952024221420288" y="5.045960903167725" z="-1.544398307800293"/>
		<particle x="-3.469466209411621" y="4.164333343505859" z="-1.545811414718628"/>
	</strand>
	<strand>
		<particle x="-1.0515029430389404" y="6.661182403564453" z="-1.339686393737793"/>
		<particle x="-1.8850703239440918" y="6.25867223739624" z="-1.5079691410064697"/>
		<particle x="-2.585127353668213" y="5.797224521636963" z="-1.0989418029785156"/>
		<particle x="-3.140596866607666" y="5.030257225036621" z="-0.9455788135528564"/>
		<particle x="-3.645282745361328" y="4.139400482177734" z="-0.9200376272201538"/>
	</strand>
	<strand>
		<particle x="-0.5670490264892578" y="6.9026007652282715" z="-0.854164183139801"/>
		<particle x="-1.4945383071899414" y="6.701415061950684" z="-0.7340015769004822"/>
		<particle x="-2.2714321613311768" y="6.220338344573975" z="-0.6472384929656982"/>
		<particle x="-2.8896403312683105" y="5.516315937042236" z="-0.5986449122428894"/>
		<particle x="-3.419530153274536" y="4.653780937194824" z="-0.5635658502578735"/>
	</strand>
	<strand>
		<particle x="-2.5698559284210205" y="5.16831636428833" z="-2.002976179122925"/>
		<particle x="-3.2466697692871094" y="4.407768726348877" z="-1.7362827062606812"/>
		<particle x="-3.8203489780426025" y="3.7388758659362793" z="-1.2915894985198975"/>
		<particle x="-4.050337791442871" y="3.1952109336853027" z="-0.5159472823143005"/>
		<particle x="-4.272908687591553" y="2.4797446727752686" z="0.23090869188308716"/>
	</strand>
	<strand>
		<particle x="-2.4374427795410156" y="5.777066230773926" z="-1.2854691743850708"/>
		<particle x="-3.117156982421875" y="5.042028427124023" z="-1.0223311185836792"/>
		<particle x="-3.6425344944000244" y="4.219601631164551" z="-0.8114917278289795"/>
		<particle x="-3.922555923461914" y="3.4376585483551025" z="-0.2990930676460266"/>
		<particle x="-4.029547214508057" y="2.7913198471069336" z="0.5178529024124146"/>
	</strand>
	<strand>
		<particle x="-1.361350655555725" y="6.661184787750244" z="-0.8442714810371399"/>
		<particle x="-2.1856722831726074" y="6.293099403381348" z="-0.46573445200920105"/>
		<particle x="-2.808668613433838" y="5.677093029022217" z="-0.11720329523086548"/>
		<particle x="-3.263225555419922" y="4.882624626159668" z="0.18605196475982666"/>
		<particle x="-3.627322196960449" y="3.9229683876037598" z="0.31564033031463623"/>
	</strand>
	<strand>
		<particle x="-2.5791261196136475" y="5.777064800262451" z="-0.7754580974578857"/>
		<particle x="-3.1960487365722656" y="5.047389507293701" z="-0.36530736088752747"/>
		<particle x="-3.6321568489074707" y="4.180418968200684" z="-0.13043302297592163"/>
		<particle x="-3.8304624557495117" y="3.244889259338379" z="0.17137068510055542"/>
		<particle x="-3.9013397693634033" y="2.397268772125244" z="0.8035969734191895"/>
	</strand>
	<strand>
		<particle x="-2.621691942214966" y="5.777045726776123" z="-0.24671117961406708"/>
		<particle x="-3.152056932449341" y="5.033016681671143" z="0.25976812839508057"/>
		<particle x="-3.5333569049835205" y="4.125575542449951" z="0.49498748779296875"/>
		<particle x="-3.4973034858703613" y="3.374882221221924" z="0.9717221260070801"/>
		<particle x="-3.4549953937530518" y="2.4582996368408203" z="1.4976038932800293"/>
	</strand>
</hair>
