<?xml version="1.0" ?>
<hair count="10" resolution="5" scale="13.17196289698283">
	<strand>
		<particle x="-0.22564759850502014" y="4.426279544830322" z="3.2513723373413086"/>
		<particle x="-0.19357022643089294" y="3.18841552734375" z="4.929947376251221"/>
		<particle x="-0.12118977308273315" y="1.6675630807876587" z="6.218269348144531"/>
		<particle x="-0.013327643275260925" y="-0.10093200206756592" z="7.163046836853027"/>
		<particle x="0.14792312681674957" y="-2.2268919944763184" z="7.4500861167907715"/>
	</strand>
	<strand>
		<particle x="-0.6096085906028748" y="4.661961555480957" z="3.1444082260131836"/>
		<particle x="-0.5874495506286621" y="3.502612829208374" z="4.875641822814941"/>
		<particle x="-0.5268344283103943" y="2.0742244720458984" z="6.254154682159424"/>
		<particle x="-0.4226195216178894" y="0.331240177154541" z="7.231129169464111"/>
		<particle x="-0.2709236145019531" y="-1.7543096542358398" z="7.743802547454834"/>
	</strand>
	<strand>
		<particle x="-0.20741598308086395" y="5.134779453277588" z="2.9643213748931885"/>
		<particle x="-0.22611762583255768" y="4.354952812194824" z="4.865495204925537"/>
		<particle x="-0.1878368854522705" y="3.128325939178467" z="6.375504970550537"/>
		<particle x="-0.08333342522382736" y="1.3925409317016602" z="7.348978519439697"/>
		<particle x="0.05229967087507248" y="-0.5983961820602417" z="8.101774215698242"/>
	</strand>
	<strand>
		<particle x="-0.5515137910842896" y="5.35198450088501" z="2.8190135955810547"/>
		<particle x="-0.5910913348197937" y="4.73699426651001" z="4.7700514793396"/>
		<particle x="-0.5629154443740845" y="3.579277992248535" z="6.341270446777344"/>
		<particle x="-0.46636998653411865" y="1.8955979347229004" z="7.379915237426758"/>
		<particle x="-0.3407970070838928" y="-0.0421595573425293" z="8.253108978271484"/>
	</strand>
	<strand>
		<particle x="0.44763392210006714" y="4.426281929016113" z="3.2288260459899902"/>
		<particle x="0.4877139925956726" y="3.1205568313598633" z="4.857856273651123"/>
		<particle x="0.5721830725669861" y="1.507483959197998" z="6.039502143859863"/>
		<particle x="0.6857596635818481" y="-0.30109500885009766" z="6.94382381439209"/>
		<particle x="0.85698401927948" y="-2.4309730529785156" z="6.901188373565674"/>
	</strand>
	<strand>
		<particle x="0.05083400011062622" y="4.661961555480957" z="3.2012181282043457"/>
		<particle x="0.07724559307098389" y="3.4697258472442627" z="4.910624027252197"/>
		<particle x="0.14503423869609833" y="1.9844166040420532" z="6.233452796936035"/>
		<particle x="0.25110870599746704" y="0.22805988788604736" z="7.196651458740234"/>
		<particle x="0.4070453345775604" y="-1.8758362531661987" z="7.6213154792785645"/>
	</strand>
	<strand>
		<particle x="0.4112822413444519" y="5.134792327880859" z="2.9437057971954346"/>
		<particle x="0.3895762860774994" y="4.38873815536499" z="4.857370376586914"/>
		<particle x="0.42519083619117737" y="3.184187889099121" z="6.387807846069336"/>
		<particle x="0.5366697907447815" y="1.407362699508667" z="7.2767558097839355"/>
		<particle x="0.6793467998504639" y="-0.6208939552307129" z="7.936652660369873"/>
	</strand>
	<strand>
		<particle x="0.046312734484672546" y="5.351984024047852" z="2.870375156402588"/>
		<particle x="0.006476283073425293" y="4.740805149078369" z="4.820230484008789"/>
		<particle x="0.03125912696123123" y="3.607172727584839" z="6.42161226272583"/>
		<particle x="0.1270701289176941" y="1.9333631992340088" z="7.448328495025635"/>
		<particle x="0.2686592936515808" y="-0.0945901870727539" z="8.113344192504883"/>
	</strand>
	<strand>
		<particle x="0.04001127928495407" y="5.960732460021973" z="2.4181580543518066"/>
		<particle x="-0.06276413798332214" y="5.855840682983398" z="4.422092437744141"/>
		<particle x="-0.05605635419487953" y="4.823247909545898" z="6.04103946685791"/>
		<particle x="-0.00606556236743927" y="3.469425678253174" z="7.457373142242432"/>
		<particle x="0.09843406081199646" y="1.662247657775879" z="8.490436553955078"/>
	</strand>
	<strand>
		<particle x="-0.5611980557441711" y="4.1419572830200195" z="3.299173355102539"/>
		<particle x="-0.530066728591919" y="2.907719135284424" z="4.9756059646606445"/>
		<particle x="-0.4474560022354126" y="1.2913458347320557" z="6.156220436096191"/>
		<particle x="-0.334511935710907" y="-0.5357691049575806" z="7.02198600769043"/>
		<particle x="-0.15496891736984253" y="-2.6678032875061035" z="6.9763665199279785"/>
	</strand>
</hair>
